[
  {
    "question": "¿Dentro de qué etiqueta HTML ponemos el código JavaScript?",
    "choice1": "<js>",
    "choice2": "<javascript>",
    "choice3": "<script>",
    "choice4": "<scripting>",
    "answer": 3
  },
  {
    "question": "¿Con qué etiqueta se puede iniciar una lista ordenada?",
    "choice1": "<ol>",
    "choice2": "<dl>",
    "choice3": "<list>",
    "choice4": "<ul>",
    "answer": 1
  },
  {
    "question": "¿Qué entidad define los estándars Web?",
    "choice1": "Google",
    "choice2": "The World Wide Web Consortium",
    "choice3": "Microsoft",
    "choice4": "Mozilla",
    "answer": 2
  },
  {
    "question": "¿Cómo se escribe un 'Hola Mundo' en una alerta?",
    "choice1": "msgBox('Hola Mundo');",
    "choice2": "alertBox('Hola Mundo');",
    "choice3": "msg('Hola Mundo');",
    "choice4": "alert('Hola Mundo');",
    "answer": 4
  }
]
